{
    "analysis": {
        "enable_decoded_strings": false,
        "enable_stack_strings": false,
        "enable_static_strings": true,
        "enable_tight_strings": false,
        "functions": {
            "analyzed_decoded_strings": 0,
            "analyzed_stack_strings": 0,
            "analyzed_tight_strings": 0,
            "decoding_function_scores": {},
            "discovered": 0,
            "library": 0
        }
    },
    "metadata": {
        "file_path": "data/unprocessed/DikeDataset-main/files/benign/2844b24385ae3e9ed11105b02ca87b7bc0e49ee5086739138640ca42b6b60df3.exe",
        "imagebase": 0,
        "min_length": 4,
        "runtime": {
            "decoded_strings": 0.0,
            "find_features": 0.0,
            "stack_strings": 0.0,
            "start_date": "2023-02-10T15:46:40.800158Z",
            "static_strings": 0.0082,
            "tight_strings": 0.0,
            "total": 0.0082,
            "vivisect": 0.0
        },
        "version": "v2.2.0-0-g783dd8f"
    },
    "strings": {
        "decoded_strings": [],
        "stack_strings": [],
        "static_strings": [
            {
                "encoding": "ASCII",
                "offset": 77,
                "string": "!This program cannot be run in DOS mode."
            },
            {
                "encoding": "ASCII",
                "offset": 376,
                "string": ".text"
            },
            {
                "encoding": "ASCII",
                "offset": 415,
                "string": "`.rsrc"
            },
            {
                "encoding": "ASCII",
                "offset": 455,
                "string": "@.reloc"
            },
            {
                "encoding": "ASCII",
                "offset": 4216,
                "string": "3{5tc"
            },
            {
                "encoding": "ASCII",
                "offset": 4649,
                "string": ",\t\to"
            },
            {
                "encoding": "ASCII",
                "offset": 4816,
                "string": "+. `"
            },
            {
                "encoding": "ASCII",
                "offset": 5076,
                "string": "BSJB"
            },
            {
                "encoding": "ASCII",
                "offset": 5092,
                "string": "v2.0.50727"
            },
            {
                "encoding": "ASCII",
                "offset": 5128,
                "string": "#Strings"
            },
            {
                "encoding": "ASCII",
                "offset": 5160,
                "string": "#GUID"
            },
            {
                "encoding": "ASCII",
                "offset": 5176,
                "string": "#Blob"
            },
            {
                "encoding": "ASCII",
                "offset": 6382,
                "string": "[&s$"
            },
            {
                "encoding": "ASCII",
                "offset": 6461,
                "string": "<Module>"
            },
            {
                "encoding": "ASCII",
                "offset": 6470,
                "string": "TsWpfWrp.exe"
            },
            {
                "encoding": "ASCII",
                "offset": 6483,
                "string": "BuildInfo"
            },
            {
                "encoding": "ASCII",
                "offset": 6493,
                "string": "Microsoft.Internal"
            },
            {
                "encoding": "ASCII",
                "offset": 6512,
                "string": "DllImport"
            },
            {
                "encoding": "ASCII",
                "offset": 6522,
                "string": "TsWpfWrapper"
            },
            {
                "encoding": "ASCII",
                "offset": 6535,
                "string": "TsWpfWrapperNameSpace"
            },
            {
                "encoding": "ASCII",
                "offset": 6557,
                "string": "mscorlib"
            },
            {
                "encoding": "ASCII",
                "offset": 6566,
                "string": "System"
            },
            {
                "encoding": "ASCII",
                "offset": 6573,
                "string": "Object"
            },
            {
                "encoding": "ASCII",
                "offset": 6580,
                "string": "WCP_PUBLIC_KEY_TOKEN"
            },
            {
                "encoding": "ASCII",
                "offset": 6601,
                "string": "WCP_PUBLIC_KEY_STRING"
            },
            {
                "encoding": "ASCII",
                "offset": 6623,
                "string": "WCP_VERSION"
            },
            {
                "encoding": "ASCII",
                "offset": 6635,
                "string": "WCP_VERSION_SUFFIX"
            },
            {
                "encoding": "ASCII",
                "offset": 6654,
                "string": "MIL_VERSION_SUFFIX"
            },
            {
                "encoding": "ASCII",
                "offset": 6673,
                "string": "PresentationCore"
            },
            {
                "encoding": "ASCII",
                "offset": 6690,
                "string": "PresentationCFFRasterizer"
            },
            {
                "encoding": "ASCII",
                "offset": 6716,
                "string": "PresentationFontCache"
            },
            {
                "encoding": "ASCII",
                "offset": 6738,
                "string": "PresentationFramework"
            },
            {
                "encoding": "ASCII",
                "offset": 6760,
                "string": "PresentationUI"
            },
            {
                "encoding": "ASCII",
                "offset": 6775,
                "string": "PresentationFrameworkLuna"
            },
            {
                "encoding": "ASCII",
                "offset": 6801,
                "string": "PresentationFrameworkRoyale"
            },
            {
                "encoding": "ASCII",
                "offset": 6829,
                "string": "PresentationFrameworkAero"
            },
            {
                "encoding": "ASCII",
                "offset": 6855,
                "string": "PresentationFrameworkClassic"
            },
            {
                "encoding": "ASCII",
                "offset": 6884,
                "string": "ReachFramework"
            },
            {
                "encoding": "ASCII",
                "offset": 6899,
                "string": "SystemPrinting"
            },
            {
                "encoding": "ASCII",
                "offset": 6914,
                "string": "SystemWindowsPresentation"
            },
            {
                "encoding": "ASCII",
                "offset": 6940,
                "string": "FontCachePortName"
            },
            {
                "encoding": "ASCII",
                "offset": 6958,
                "string": "FontCacheServiceName"
            },
            {
                "encoding": "ASCII",
                "offset": 6979,
                "string": "PresentationNative"
            },
            {
                "encoding": "ASCII",
                "offset": 6998,
                "string": "PresentationCFFRasterizerNative"
            },
            {
                "encoding": "ASCII",
                "offset": 7030,
                "string": "MilCore"
            },
            {
                "encoding": "ASCII",
                "offset": 7038,
                "string": "Wininet"
            },
            {
                "encoding": "ASCII",
                "offset": 7046,
                "string": "WindowsCodecs"
            },
            {
                "encoding": "ASCII",
                "offset": 7060,
                "string": "WindowsCodecsExt"
            },
            {
                "encoding": "ASCII",
                "offset": 7077,
                "string": "Mscms"
            },
            {
                "encoding": "ASCII",
                "offset": 7083,
                "string": "PrntvPt"
            },
            {
                "encoding": "ASCII",
                "offset": 7091,
                "string": "Main"
            },
            {
                "encoding": "ASCII",
                "offset": 7096,
                "string": "System.Printing"
            },
            {
                "encoding": "ASCII",
                "offset": 7112,
                "string": "PrintQueue"
            },
            {
                "encoding": "ASCII",
                "offset": 7123,
                "string": "WaitForJobToBePrinted"
            },
            {
                "encoding": "ASCII",
                "offset": 7145,
                "string": "PrintXPSDocument"
            },
            {
                "encoding": "ASCII",
                "offset": 7162,
                "string": "GetPrintQueue"
            },
            {
                "encoding": "ASCII",
                "offset": 7176,
                "string": ".ctor"
            },
            {
                "encoding": "ASCII",
                "offset": 7182,
                "string": "System.Reflection"
            },
            {
                "encoding": "ASCII",
                "offset": 7200,
                "string": "AssemblyDelaySignAttribute"
            },
            {
                "encoding": "ASCII",
                "offset": 7227,
                "string": "AssemblyKeyFileAttribute"
            },
            {
                "encoding": "ASCII",
                "offset": 7252,
                "string": "AssemblyFileVersionAttribute"
            },
            {
                "encoding": "ASCII",
                "offset": 7281,
                "string": "AssemblyCompanyAttribute"
            },
            {
                "encoding": "ASCII",
                "offset": 7306,
                "string": "AssemblyCopyrightAttribute"
            },
            {
                "encoding": "ASCII",
                "offset": 7333,
                "string": "AssemblyProductAttribute"
            },
            {
                "encoding": "ASCII",
                "offset": 7358,
                "string": "AssemblyVersionAttribute"
            },
            {
                "encoding": "ASCII",
                "offset": 7383,
                "string": "System.Runtime.InteropServices"
            },
            {
                "encoding": "ASCII",
                "offset": 7414,
                "string": "ComVisibleAttribute"
            },
            {
                "encoding": "ASCII",
                "offset": 7434,
                "string": "CLSCompliantAttribute"
            },
            {
                "encoding": "ASCII",
                "offset": 7456,
                "string": "System.Security.Permissions"
            },
            {
                "encoding": "ASCII",
                "offset": 7484,
                "string": "SecurityPermissionAttribute"
            },
            {
                "encoding": "ASCII",
                "offset": 7512,
                "string": "SecurityAction"
            },
            {
                "encoding": "ASCII",
                "offset": 7527,
                "string": "System.Diagnostics"
            },
            {
                "encoding": "ASCII",
                "offset": 7546,
                "string": "DebuggableAttribute"
            },
            {
                "encoding": "ASCII",
                "offset": 7566,
                "string": "DebuggingModes"
            },
            {
                "encoding": "ASCII",
                "offset": 7581,
                "string": "System.Runtime.CompilerServices"
            },
            {
                "encoding": "ASCII",
                "offset": 7613,
                "string": "CompilationRelaxationsAttribute"
            },
            {
                "encoding": "ASCII",
                "offset": 7645,
                "string": "RuntimeCompatibilityAttribute"
            },
            {
                "encoding": "ASCII",
                "offset": 7675,
                "string": "TsWpfWrp"
            },
            {
                "encoding": "ASCII",
                "offset": 7684,
                "string": "STAThreadAttribute"
            },
            {
                "encoding": "ASCII",
                "offset": 7703,
                "string": "args"
            },
            {
                "encoding": "ASCII",
                "offset": 7708,
                "string": "String"
            },
            {
                "encoding": "ASCII",
                "offset": 7715,
                "string": "op_Equality"
            },
            {
                "encoding": "ASCII",
                "offset": 7727,
                "string": "Console"
            },
            {
                "encoding": "ASCII",
                "offset": 7735,
                "string": "WriteLine"
            },
            {
                "encoding": "ASCII",
                "offset": 7745,
                "string": "Concat"
            },
            {
                "encoding": "ASCII",
                "offset": 7752,
                "string": "System.IO"
            },
            {
                "encoding": "ASCII",
                "offset": 7762,
                "string": "File"
            },
            {
                "encoding": "ASCII",
                "offset": 7767,
                "string": "Delete"
            },
            {
                "encoding": "ASCII",
                "offset": 7774,
                "string": "Exception"
            },
            {
                "encoding": "ASCII",
                "offset": 7784,
                "string": "myPrinter"
            },
            {
                "encoding": "ASCII",
                "offset": 7794,
                "string": "interactiveMode"
            },
            {
                "encoding": "ASCII",
                "offset": 7810,
                "string": "DateTime"
            },
            {
                "encoding": "ASCII",
                "offset": 7819,
                "string": "MinValue"
            },
            {
                "encoding": "ASCII",
                "offset": 7828,
                "string": "PrintJobInfoCollection"
            },
            {
                "encoding": "ASCII",
                "offset": 7851,
                "string": "GetPrintJobInfoCollection"
            },
            {
                "encoding": "ASCII",
                "offset": 7877,
                "string": "System.Collections.Generic"
            },
            {
                "encoding": "ASCII",
                "offset": 7904,
                "string": "IEnumerator`1"
            },
            {
                "encoding": "ASCII",
                "offset": 7918,
                "string": "PrintSystemJobInfo"
            },
            {
                "encoding": "ASCII",
                "offset": 7937,
                "string": "GetEnumerator"
            },
            {
                "encoding": "ASCII",
                "offset": 7951,
                "string": "get_Current"
            },
            {
                "encoding": "ASCII",
                "offset": 7963,
                "string": "get_TimeJobSubmitted"
            },
            {
                "encoding": "ASCII",
                "offset": 7984,
                "string": "op_LessThan"
            },
            {
                "encoding": "ASCII",
                "offset": 7996,
                "string": "System.Collections"
            },
            {
                "encoding": "ASCII",
                "offset": 8015,
                "string": "IEnumerator"
            },
            {
                "encoding": "ASCII",
                "offset": 8027,
                "string": "MoveNext"
            },
            {
                "encoding": "ASCII",
                "offset": 8036,
                "string": "IDisposable"
            },
            {
                "encoding": "ASCII",
                "offset": 8048,
                "string": "Dispose"
            },
            {
                "encoding": "ASCII",
                "offset": 8056,
                "string": "PrintSystemObject"
            },
            {
                "encoding": "ASCII",
                "offset": 8074,
                "string": "get_Name"
            },
            {
                "encoding": "ASCII",
                "offset": 8083,
                "string": "Int32"
            },
            {
                "encoding": "ASCII",
                "offset": 8089,
                "string": "Microsoft.Win32"
            },
            {
                "encoding": "ASCII",
                "offset": 8105,
                "string": "Registry"
            },
            {
                "encoding": "ASCII",
                "offset": 8114,
                "string": "GetValue"
            },
            {
                "encoding": "ASCII",
                "offset": 8123,
                "string": "TimeSpan"
            },
            {
                "encoding": "ASCII",
                "offset": 8132,
                "string": "FromMinutes"
            },
            {
                "encoding": "ASCII",
                "offset": 8144,
                "string": "ToString"
            },
            {
                "encoding": "ASCII",
                "offset": 8153,
                "string": "get_Now"
            },
            {
                "encoding": "ASCII",
                "offset": 8161,
                "string": "System.Threading"
            },
            {
                "encoding": "ASCII",
                "offset": 8178,
                "string": "Thread"
            },
            {
                "encoding": "ASCII",
                "offset": 8185,
                "string": "Sleep"
            },
            {
                "encoding": "ASCII",
                "offset": 8191,
                "string": "Refresh"
            },
            {
                "encoding": "ASCII",
                "offset": 8199,
                "string": "get_IsPrinted"
            },
            {
                "encoding": "ASCII",
                "offset": 8213,
                "string": "get_IsDeleted"
            },
            {
                "encoding": "ASCII",
                "offset": 8227,
                "string": "op_Subtraction"
            },
            {
                "encoding": "ASCII",
                "offset": 8242,
                "string": "System.Security"
            },
            {
                "encoding": "ASCII",
                "offset": 8258,
                "string": "SecurityException"
            },
            {
                "encoding": "ASCII",
                "offset": 8276,
                "string": "printQueueName"
            },
            {
                "encoding": "ASCII",
                "offset": 8291,
                "string": "xpsFileName"
            },
            {
                "encoding": "ASCII",
                "offset": 8303,
                "string": "System.Windows.Xps"
            },
            {
                "encoding": "ASCII",
                "offset": 8322,
                "string": "XpsDocumentWriter"
            },
            {
                "encoding": "ASCII",
                "offset": 8340,
                "string": "CreateXpsDocumentWriter"
            },
            {
                "encoding": "ASCII",
                "offset": 8364,
                "string": "XpsDocumentNotificationLevel"
            },
            {
                "encoding": "ASCII",
                "offset": 8393,
                "string": "Write"
            },
            {
                "encoding": "ASCII",
                "offset": 8399,
                "string": "PrinterFullName"
            },
            {
                "encoding": "ASCII",
                "offset": 8415,
                "string": "StringComparison"
            },
            {
                "encoding": "ASCII",
                "offset": 8432,
                "string": "StartsWith"
            },
            {
                "encoding": "ASCII",
                "offset": 8443,
                "string": "LastIndexOf"
            },
            {
                "encoding": "ASCII",
                "offset": 8455,
                "string": "Substring"
            },
            {
                "encoding": "ASCII",
                "offset": 8465,
                "string": "PrintServer"
            },
            {
                "encoding": "ASCII",
                "offset": 8477,
                "string": "LocalPrintServer"
            },
            {
                "encoding": "ASCII",
                "offset": 8494,
                "string": "UnverifiableCodeAttribute"
            },
            {
                "encoding": "ASCII",
                "offset": 18517,
                "string": "RSA1"
            },
            {
                "encoding": "ASCII",
                "offset": 18579,
                "string": "`!g-"
            },
            {
                "encoding": "ASCII",
                "offset": 18897,
                "string": "Bd:\\sp1qfe.public.amd64fre\\internal\\strongnamekeys\\fake\\windows.snk"
            },
            {
                "encoding": "ASCII",
                "offset": 18970,
                "string": "6.0.6001.17014"
            },
            {
                "encoding": "ASCII",
                "offset": 18990,
                "string": "Microsoft Corporation"
            },
            {
                "encoding": "ASCII",
                "offset": 19016,
                "string": "9Copyright (c) Microsoft Corporation. All rights reserved."
            },
            {
                "encoding": "ASCII",
                "offset": 19079,
                "string": "*Microsoft (R) Windows (R) Operating System"
            },
            {
                "encoding": "ASCII",
                "offset": 19156,
                "string": "WrapNonExceptionThrows"
            },
            {
                "encoding": "ASCII",
                "offset": 19185,
                "string": "System.Security.Permissions.SecurityPermissionAttribute, mscorlib, Version=2.0.0.0, Culture=neutral, PublicKeyToken=b77a5c561934e089"
            },
            {
                "encoding": "ASCII",
                "offset": 19322,
                "string": "SkipVerification"
            },
            {
                "encoding": "ASCII",
                "offset": 19368,
                "string": "RSDS"
            },
            {
                "encoding": "ASCII",
                "offset": 19376,
                "string": "W>NM"
            },
            {
                "encoding": "ASCII",
                "offset": 19392,
                "string": "TsWpfWrp.pdb"
            },
            {
                "encoding": "ASCII",
                "offset": 19522,
                "string": "_CorExeMain"
            },
            {
                "encoding": "ASCII",
                "offset": 19534,
                "string": "mscoree.dll"
            },
            {
                "encoding": "ASCII",
                "offset": 28734,
                "string": ">0<0"
            },
            {
                "encoding": "ASCII",
                "offset": 28762,
                "string": "0!0\t"
            },
            {
                "encoding": "ASCII",
                "offset": 28876,
                "string": "Washington1"
            },
            {
                "encoding": "ASCII",
                "offset": 28897,
                "string": "Redmond1"
            },
            {
                "encoding": "ASCII",
                "offset": 28915,
                "string": "Microsoft Corporation1!0"
            },
            {
                "encoding": "ASCII",
                "offset": 28947,
                "string": "Microsoft Time-Stamp PCA0"
            },
            {
                "encoding": "ASCII",
                "offset": 28975,
                "string": "150320173203Z"
            },
            {
                "encoding": "ASCII",
                "offset": 28990,
                "string": "160620173203Z0"
            },
            {
                "encoding": "ASCII",
                "offset": 29030,
                "string": "Washington1"
            },
            {
                "encoding": "ASCII",
                "offset": 29051,
                "string": "Redmond1"
            },
            {
                "encoding": "ASCII",
                "offset": 29069,
                "string": "Microsoft Corporation1"
            },
            {
                "encoding": "ASCII",
                "offset": 29101,
                "string": "MOPR1'0%"
            },
            {
                "encoding": "ASCII",
                "offset": 29116,
                "string": "nCipher DSE ESN:B8EC-30A4-71441%0#"
            },
            {
                "encoding": "ASCII",
                "offset": 29157,
                "string": "Microsoft Time-Stamp Service0"
            },
            {
                "encoding": "ASCII",
                "offset": 29225,
                "string": "o!6("
            },
            {
                "encoding": "ASCII",
                "offset": 29230,
                "string": "f3:f"
            },
            {
                "encoding": "ASCII",
                "offset": 29241,
                "string": "(4JC2"
            },
            {
                "encoding": "ASCII",
                "offset": 29318,
                "string": "4N}o"
            },
            {
                "encoding": "ASCII",
                "offset": 29342,
                "string": "T*9Q"
            },
            {
                "encoding": "ASCII",
                "offset": 29559,
                "string": "M0K0I"
            },
            {
                "encoding": "ASCII",
                "offset": 29569,
                "string": "Chttp://crl.microsoft.com/pki/crl/products/MicrosoftTimeStampPCA.crl0X"
            },
            {
                "encoding": "ASCII",
                "offset": 29650,
                "string": "L0J0H"
            },
            {
                "encoding": "ASCII",
                "offset": 29666,
                "string": "<http://www.microsoft.com/pki/certs/MicrosoftTimeStampPCA.crt0"
            },
            {
                "encoding": "ASCII",
                "offset": 29811,
                "string": "8QAr"
            },
            {
                "encoding": "ASCII",
                "offset": 29898,
                "string": "@#X,"
            },
            {
                "encoding": "ASCII",
                "offset": 29993,
                "string": "(}fBS"
            },
            {
                "encoding": "ASCII",
                "offset": 30099,
                "string": "Washington1"
            },
            {
                "encoding": "ASCII",
                "offset": 30120,
                "string": "Redmond1"
            },
            {
                "encoding": "ASCII",
                "offset": 30138,
                "string": "Microsoft Corporation1#0!"
            },
            {
                "encoding": "ASCII",
                "offset": 30170,
                "string": "Microsoft Code Signing PCA0"
            },
            {
                "encoding": "ASCII",
                "offset": 30200,
                "string": "140422173900Z"
            },
            {
                "encoding": "ASCII",
                "offset": 30215,
                "string": "150722173900Z0"
            },
            {
                "encoding": "ASCII",
                "offset": 30255,
                "string": "Washington1"
            },
            {
                "encoding": "ASCII",
                "offset": 30276,
                "string": "Redmond1"
            },
            {
                "encoding": "ASCII",
                "offset": 30294,
                "string": "Microsoft Corporation1"
            },
            {
                "encoding": "ASCII",
                "offset": 30326,
                "string": "MOPR1"
            },
            {
                "encoding": "ASCII",
                "offset": 30341,
                "string": "Microsoft Corporation0"
            },
            {
                "encoding": "ASCII",
                "offset": 30454,
                "string": " a@S1"
            },
            {
                "encoding": "ASCII",
                "offset": 30489,
                "string": "pI'^|g"
            },
            {
                "encoding": "ASCII",
                "offset": 30519,
                "string": "LpE8-"
            },
            {
                "encoding": "ASCII",
                "offset": 30728,
                "string": "F0D1"
            },
            {
                "encoding": "ASCII",
                "offset": 30742,
                "string": "MOPR1301"
            },
            {
                "encoding": "ASCII",
                "offset": 30756,
                "string": "*31595+b4218f13-6fca-490f-9c47-3fc557dfc4400"
            },
            {
                "encoding": "ASCII",
                "offset": 30840,
                "string": "O0M0K"
            },
            {
                "encoding": "ASCII",
                "offset": 30850,
                "string": "Ehttp://crl.microsoft.com/pki/crl/products/MicCodSigPCA_08-31-2010.crl0Z"
            },
            {
                "encoding": "ASCII",
                "offset": 30933,
                "string": "N0L0J"
            },
            {
                "encoding": "ASCII",
                "offset": 30949,
                "string": ">http://www.microsoft.com/pki/certs/MicCodSigPCA_08-31-2010.crt0"
            },
            {
                "encoding": "ASCII",
                "offset": 31348,
                "string": "com1"
            },
            {
                "encoding": "ASCII",
                "offset": 31368,
                "string": "\tmicrosoft1-0+"
            },
            {
                "encoding": "ASCII",
                "offset": 31388,
                "string": "$Microsoft Root Certificate Authority0"
            },
            {
                "encoding": "ASCII",
                "offset": 31429,
                "string": "100831221932Z"
            },
            {
                "encoding": "ASCII",
                "offset": 31444,
                "string": "200831222932Z0y1"
            },
            {
                "encoding": "ASCII",
                "offset": 31483,
                "string": "Washington1"
            },
            {
                "encoding": "ASCII",
                "offset": 31504,
                "string": "Redmond1"
            },
            {
                "encoding": "ASCII",
                "offset": 31522,
                "string": "Microsoft Corporation1#0!"
            },
            {
                "encoding": "ASCII",
                "offset": 31554,
                "string": "Microsoft Code Signing PCA0"
            },
            {
                "encoding": "ASCII",
                "offset": 31623,
                "string": "`  B"
            },
            {
                "encoding": "ASCII",
                "offset": 31628,
                "string": "vSl>"
            },
            {
                "encoding": "ASCII",
                "offset": 31778,
                "string": "_F1P"
            },
            {
                "encoding": "ASCII",
                "offset": 32043,
                "string": "`@V'"
            },
            {
                "encoding": "ASCII",
                "offset": 32068,
                "string": "I0G0E"
            },
            {
                "encoding": "ASCII",
                "offset": 32078,
                "string": "?http://crl.microsoft.com/pki/crl/products/microsoftrootcert.crl0T"
            },
            {
                "encoding": "ASCII",
                "offset": 32155,
                "string": "H0F0D"
            },
            {
                "encoding": "ASCII",
                "offset": 32171,
                "string": "8http://www.microsoft.com/pki/certs/MicrosoftRootCert.crt0"
            },
            {
                "encoding": "ASCII",
                "offset": 32421,
                "string": "ycVD"
            },
            {
                "encoding": "ASCII",
                "offset": 32436,
                "string": "ED/_"
            },
            {
                "encoding": "ASCII",
                "offset": 32471,
                "string": "&\te8"
            },
            {
                "encoding": "ASCII",
                "offset": 32527,
                "string": "N=|)H"
            },
            {
                "encoding": "ASCII",
                "offset": 32624,
                "string": "`Ge`@N"
            },
            {
                "encoding": "ASCII",
                "offset": 32820,
                "string": "com1"
            },
            {
                "encoding": "ASCII",
                "offset": 32840,
                "string": "\tmicrosoft1-0+"
            },
            {
                "encoding": "ASCII",
                "offset": 32860,
                "string": "$Microsoft Root Certificate Authority0"
            },
            {
                "encoding": "ASCII",
                "offset": 32901,
                "string": "070403125309Z"
            },
            {
                "encoding": "ASCII",
                "offset": 32916,
                "string": "210403130309Z0w1"
            },
            {
                "encoding": "ASCII",
                "offset": 32955,
                "string": "Washington1"
            },
            {
                "encoding": "ASCII",
                "offset": 32976,
                "string": "Redmond1"
            },
            {
                "encoding": "ASCII",
                "offset": 32994,
                "string": "Microsoft Corporation1!0"
            },
            {
                "encoding": "ASCII",
                "offset": 33026,
                "string": "Microsoft Time-Stamp PCA0"
            },
            {
                "encoding": "ASCII",
                "offset": 33091,
                "string": "*|k."
            },
            {
                "encoding": "ASCII",
                "offset": 33207,
                "string": "(F.'"
            },
            {
                "encoding": "ASCII",
                "offset": 33306,
                "string": "xA1w"
            },
            {
                "encoding": "ASCII",
                "offset": 33450,
                "string": "`@V'"
            },
            {
                "encoding": "ASCII",
                "offset": 33470,
                "string": "a0_1"
            },
            {
                "encoding": "ASCII",
                "offset": 33491,
                "string": "com1"
            },
            {
                "encoding": "ASCII",
                "offset": 33511,
                "string": "\tmicrosoft1-0+"
            },
            {
                "encoding": "ASCII",
                "offset": 33531,
                "string": "$Microsoft Root Certificate Authority"
            },
            {
                "encoding": "ASCII",
                "offset": 33584,
                "string": ".e0P"
            },
            {
                "encoding": "ASCII",
                "offset": 33594,
                "string": "I0G0E"
            },
            {
                "encoding": "ASCII",
                "offset": 33604,
                "string": "?http://crl.microsoft.com/pki/crl/products/microsoftrootcert.crl0T"
            },
            {
                "encoding": "ASCII",
                "offset": 33681,
                "string": "H0F0D"
            },
            {
                "encoding": "ASCII",
                "offset": 33697,
                "string": "8http://www.microsoft.com/pki/certs/MicrosoftRootCert.crt0"
            },
            {
                "encoding": "ASCII",
                "offset": 33815,
                "string": ".tq[m"
            },
            {
                "encoding": "ASCII",
                "offset": 33900,
                "string": "*$\"p"
            },
            {
                "encoding": "ASCII",
                "offset": 33949,
                "string": "1Jv1=+r"
            },
            {
                "encoding": "ASCII",
                "offset": 33998,
                "string": "xe\\["
            },
            {
                "encoding": "ASCII",
                "offset": 34088,
                "string": "qZFC"
            },
            {
                "encoding": "ASCII",
                "offset": 34134,
                "string": "L&*H$_Z"
            },
            {
                "encoding": "ASCII",
                "offset": 34241,
                "string": "u\"/2"
            },
            {
                "encoding": "ASCII",
                "offset": 34347,
                "string": "Washington1"
            },
            {
                "encoding": "ASCII",
                "offset": 34368,
                "string": "Redmond1"
            },
            {
                "encoding": "ASCII",
                "offset": 34386,
                "string": "Microsoft Corporation1#0!"
            },
            {
                "encoding": "ASCII",
                "offset": 34418,
                "string": "Microsoft Code Signing PCA"
            },
            {
                "encoding": "ASCII",
                "offset": 34587,
                "string": "1604"
            },
            {
                "encoding": "ASCII",
                "offset": 34623,
                "string": "http://microsoft.com0"
            },
            {
                "encoding": "ASCII",
                "offset": 34676,
                "string": "_p\"y"
            },
            {
                "encoding": "ASCII",
                "offset": 34814,
                "string": "S`(31"
            },
            {
                "encoding": "ASCII",
                "offset": 34977,
                "string": "Washington1"
            },
            {
                "encoding": "ASCII",
                "offset": 34998,
                "string": "Redmond1"
            },
            {
                "encoding": "ASCII",
                "offset": 35016,
                "string": "Microsoft Corporation1!0"
            },
            {
                "encoding": "ASCII",
                "offset": 35048,
                "string": "Microsoft Time-Stamp PCA"
            },
            {
                "encoding": "ASCII",
                "offset": 35149,
                "string": "150507113801Z0#"
            },
            {
                "encoding": "ASCII",
                "offset": 35275,
                "string": "1wY|P"
            },
            {
                "encoding": "UTF-16LE",
                "offset": 8522,
                "string": "/nodebug"
            },
            {
                "encoding": "UTF-16LE",
                "offset": 8540,
                "string": "Usage: TsWpfWrp.exe <PrinterName> <XPSFile> [/nodebug]"
            },
            {
                "encoding": "UTF-16LE",
                "offset": 8650,
                "string": "Printer       :"
            },
            {
                "encoding": "UTF-16LE",
                "offset": 8682,
                "string": "File          :"
            },
            {
                "encoding": "UTF-16LE",
                "offset": 8714,
                "string": "Error printing:"
            },
            {
                "encoding": "UTF-16LE",
                "offset": 8746,
                "string": "Error deleting ( "
            },
            {
                "encoding": "UTF-16LE",
                "offset": 8790,
                "string": "Error waiting for jobto complete:"
            },
            {
                "encoding": "UTF-16LE",
                "offset": 8858,
                "string": "Waiting For Job to be printed       :"
            },
            {
                "encoding": "UTF-16LE",
                "offset": 8934,
                "string": "HKEY_CURRENT_USER\\Software\\Microsoft\\Terminal Server Client"
            },
            {
                "encoding": "UTF-16LE",
                "offset": 9054,
                "string": "TSWpfWrpTimeOut"
            },
            {
                "encoding": "UTF-16LE",
                "offset": 9086,
                "string": "Will Wait For = "
            },
            {
                "encoding": "UTF-16LE",
                "offset": 9120,
                "string": "Job Was Printed or Cancelled!"
            },
            {
                "encoding": "UTF-16LE",
                "offset": 9180,
                "string": "Job Was not printed, giving up!"
            },
            {
                "encoding": "UTF-16LE",
                "offset": 9244,
                "string": "JobQueue was empty, not waiting for printing."
            },
            {
                "encoding": "UTF-16LE",
                "offset": 9374,
                "string": "31bf3856ad364e35"
            },
            {
                "encoding": "UTF-16LE",
                "offset": 9408,
                "string": "0024000004800000940000000602000000240000525341310004000001000100b5fc90e7027f67871e773a8fde8938c81dd402ba65b9201d60593e96c492651e889cc13f1415ebb53fac1131ae0bd333c5ee6021672d9718ea31a8aebd0da0072f25d87dba6fc90ffd598ed4da35e44c398c454307e8e33b8426143daec9f596836f97c8f74750e5975c64e2189f45def46b2a2b1247adc3652bf5c308055da9"
            },
            {
                "encoding": "UTF-16LE",
                "offset": 10049,
                "string": "3.0.0.0"
            },
            {
                "encoding": "UTF-16LE",
                "offset": 10064,
                "string": "_v0300"
            },
            {
                "encoding": "UTF-16LE",
                "offset": 10078,
                "string": "PresentationCore, PublicKey=0024000004800000940000000602000000240000525341310004000001000100b5fc90e7027f67871e773a8fde8938c81dd402ba65b9201d60593e96c492651e889cc13f1415ebb53fac1131ae0bd333c5ee6021672d9718ea31a8aebd0da0072f25d87dba6fc90ffd598ed4da35e44c398c454307e8e33b8426143daec9f596836f97c8f74750e5975c64e2189f45def46b2a2b1247adc3652bf5c308055da9"
            },
            {
                "encoding": "UTF-16LE",
                "offset": 10776,
                "string": "PresentationCFFRasterizer, PublicKey=0024000004800000940000000602000000240000525341310004000001000100b5fc90e7027f67871e773a8fde8938c81dd402ba65b9201d60593e96c492651e889cc13f1415ebb53fac1131ae0bd333c5ee6021672d9718ea31a8aebd0da0072f25d87dba6fc90ffd598ed4da35e44c398c454307e8e33b8426143daec9f596836f97c8f74750e5975c64e2189f45def46b2a2b1247adc3652bf5c308055da9"
            },
            {
                "encoding": "UTF-16LE",
                "offset": 11492,
                "string": "PresentationFontCache, PublicKey=0024000004800000940000000602000000240000525341310004000001000100b5fc90e7027f67871e773a8fde8938c81dd402ba65b9201d60593e96c492651e889cc13f1415ebb53fac1131ae0bd333c5ee6021672d9718ea31a8aebd0da0072f25d87dba6fc90ffd598ed4da35e44c398c454307e8e33b8426143daec9f596836f97c8f74750e5975c64e2189f45def46b2a2b1247adc3652bf5c308055da9"
            },
            {
                "encoding": "UTF-16LE",
                "offset": 12200,
                "string": "PresentationFramework, PublicKey=0024000004800000940000000602000000240000525341310004000001000100b5fc90e7027f67871e773a8fde8938c81dd402ba65b9201d60593e96c492651e889cc13f1415ebb53fac1131ae0bd333c5ee6021672d9718ea31a8aebd0da0072f25d87dba6fc90ffd598ed4da35e44c398c454307e8e33b8426143daec9f596836f97c8f74750e5975c64e2189f45def46b2a2b1247adc3652bf5c308055da9"
            },
            {
                "encoding": "UTF-16LE",
                "offset": 12908,
                "string": "PresentationUI, PublicKey=0024000004800000940000000602000000240000525341310004000001000100b5fc90e7027f67871e773a8fde8938c81dd402ba65b9201d60593e96c492651e889cc13f1415ebb53fac1131ae0bd333c5ee6021672d9718ea31a8aebd0da0072f25d87dba6fc90ffd598ed4da35e44c398c454307e8e33b8426143daec9f596836f97c8f74750e5975c64e2189f45def46b2a2b1247adc3652bf5c308055da9"
            },
            {
                "encoding": "UTF-16LE",
                "offset": 13602,
                "string": "PresentationFramework.Luna, PublicKey=0024000004800000940000000602000000240000525341310004000001000100b5fc90e7027f67871e773a8fde8938c81dd402ba65b9201d60593e96c492651e889cc13f1415ebb53fac1131ae0bd333c5ee6021672d9718ea31a8aebd0da0072f25d87dba6fc90ffd598ed4da35e44c398c454307e8e33b8426143daec9f596836f97c8f74750e5975c64e2189f45def46b2a2b1247adc3652bf5c308055da9"
            },
            {
                "encoding": "UTF-16LE",
                "offset": 14320,
                "string": "PresentationFramework.Royale, PublicKey=0024000004800000940000000602000000240000525341310004000001000100b5fc90e7027f67871e773a8fde8938c81dd402ba65b9201d60593e96c492651e889cc13f1415ebb53fac1131ae0bd333c5ee6021672d9718ea31a8aebd0da0072f25d87dba6fc90ffd598ed4da35e44c398c454307e8e33b8426143daec9f596836f97c8f74750e5975c64e2189f45def46b2a2b1247adc3652bf5c308055da9"
            },
            {
                "encoding": "UTF-16LE",
                "offset": 15042,
                "string": "PresentationFramework.Aero, PublicKey=0024000004800000940000000602000000240000525341310004000001000100b5fc90e7027f67871e773a8fde8938c81dd402ba65b9201d60593e96c492651e889cc13f1415ebb53fac1131ae0bd333c5ee6021672d9718ea31a8aebd0da0072f25d87dba6fc90ffd598ed4da35e44c398c454307e8e33b8426143daec9f596836f97c8f74750e5975c64e2189f45def46b2a2b1247adc3652bf5c308055da9"
            },
            {
                "encoding": "UTF-16LE",
                "offset": 15760,
                "string": "PresentationFramework.Classic, PublicKey=0024000004800000940000000602000000240000525341310004000001000100b5fc90e7027f67871e773a8fde8938c81dd402ba65b9201d60593e96c492651e889cc13f1415ebb53fac1131ae0bd333c5ee6021672d9718ea31a8aebd0da0072f25d87dba6fc90ffd598ed4da35e44c398c454307e8e33b8426143daec9f596836f97c8f74750e5975c64e2189f45def46b2a2b1247adc3652bf5c308055da9"
            },
            {
                "encoding": "UTF-16LE",
                "offset": 16484,
                "string": "ReachFramework, PublicKey=0024000004800000940000000602000000240000525341310004000001000100b5fc90e7027f67871e773a8fde8938c81dd402ba65b9201d60593e96c492651e889cc13f1415ebb53fac1131ae0bd333c5ee6021672d9718ea31a8aebd0da0072f25d87dba6fc90ffd598ed4da35e44c398c454307e8e33b8426143daec9f596836f97c8f74750e5975c64e2189f45def46b2a2b1247adc3652bf5c308055da9"
            },
            {
                "encoding": "UTF-16LE",
                "offset": 17178,
                "string": "System.Printing, PublicKey=0024000004800000940000000602000000240000525341310004000001000100b5fc90e7027f67871e773a8fde8938c81dd402ba65b9201d60593e96c492651e889cc13f1415ebb53fac1131ae0bd333c5ee6021672d9718ea31a8aebd0da0072f25d87dba6fc90ffd598ed4da35e44c398c454307e8e33b8426143daec9f596836f97c8f74750e5975c64e2189f45def46b2a2b1247adc3652bf5c308055da9"
            },
            {
                "encoding": "UTF-16LE",
                "offset": 17874,
                "string": "System.Windows.Presentation, PublicKey=00000000000000000400000000000000"
            },
            {
                "encoding": "UTF-16LE",
                "offset": 18017,
                "string": "\\BaseNamedObjects\\FontCachePort3.0.0.0"
            },
            {
                "encoding": "UTF-16LE",
                "offset": 18094,
                "string": "FontCache3.0.0.0"
            },
            {
                "encoding": "UTF-16LE",
                "offset": 18127,
                "string": "PresentationNative_v0300.dll"
            },
            {
                "encoding": "UTF-16LE",
                "offset": 18184,
                "string": "PresentationCFFRasterizerNative_v0300.dll"
            },
            {
                "encoding": "UTF-16LE",
                "offset": 18267,
                "string": "MilCore.dll"
            },
            {
                "encoding": "UTF-16LE",
                "offset": 18290,
                "string": "Wininet.dll"
            },
            {
                "encoding": "UTF-16LE",
                "offset": 18313,
                "string": "WindowsCodecs.dll"
            },
            {
                "encoding": "UTF-16LE",
                "offset": 18348,
                "string": "WindowsCodecsExt.dll"
            },
            {
                "encoding": "UTF-16LE",
                "offset": 18389,
                "string": "mscms.dll"
            },
            {
                "encoding": "UTF-16LE",
                "offset": 18408,
                "string": "prntvpt.dll"
            },
            {
                "encoding": "UTF-16LE",
                "offset": 20574,
                "string": "VS_VERSION_INFO"
            },
            {
                "encoding": "UTF-16LE",
                "offset": 20666,
                "string": "StringFileInfo"
            },
            {
                "encoding": "UTF-16LE",
                "offset": 20702,
                "string": "040904B0"
            },
            {
                "encoding": "UTF-16LE",
                "offset": 20726,
                "string": "CompanyName"
            },
            {
                "encoding": "UTF-16LE",
                "offset": 20752,
                "string": "Microsoft Corporation"
            },
            {
                "encoding": "UTF-16LE",
                "offset": 20802,
                "string": "FileDescription"
            },
            {
                "encoding": "UTF-16LE",
                "offset": 20836,
                "string": "Windows Presentation Foundation Terminal Server Print Wrapper"
            },
            {
                "encoding": "UTF-16LE",
                "offset": 20966,
                "string": "FileVersion"
            },
            {
                "encoding": "UTF-16LE",
                "offset": 20992,
                "string": "3.0.6920.1210 (lh_tools_devdiv_wpf_sp1qfe.140326-0902)"
            },
            {
                "encoding": "UTF-16LE",
                "offset": 21110,
                "string": "InternalName"
            },
            {
                "encoding": "UTF-16LE",
                "offset": 21136,
                "string": "TsWpfWrp"
            },
            {
                "encoding": "UTF-16LE",
                "offset": 21162,
                "string": "LegalCopyright"
            },
            {
                "encoding": "UTF-16LE",
                "offset": 21194,
                "string": " Microsoft Corporation. All rights reserved."
            },
            {
                "encoding": "UTF-16LE",
                "offset": 21290,
                "string": "OriginalFilename"
            },
            {
                "encoding": "UTF-16LE",
                "offset": 21324,
                "string": "TsWpfWrp.exe"
            },
            {
                "encoding": "UTF-16LE",
                "offset": 21358,
                "string": "ProductName"
            },
            {
                "encoding": "UTF-16LE",
                "offset": 21384,
                "string": "Microsoft"
            },
            {
                "encoding": "UTF-16LE",
                "offset": 21404,
                "string": " Windows"
            },
            {
                "encoding": "UTF-16LE",
                "offset": 21422,
                "string": " Operating System"
            },
            {
                "encoding": "UTF-16LE",
                "offset": 21466,
                "string": "ProductVersion"
            },
            {
                "encoding": "UTF-16LE",
                "offset": 21496,
                "string": "3.0.6920.0"
            },
            {
                "encoding": "UTF-16LE",
                "offset": 21526,
                "string": "VarFileInfo"
            },
            {
                "encoding": "UTF-16LE",
                "offset": 21558,
                "string": "Translation"
            },
            {
                "encoding": "UTF-16LE",
                "offset": 32018,
                "string": "SubC"
            },
            {
                "encoding": "UTF-16LE",
                "offset": 34596,
                "string": "TSWPFWrp.ex"
            }
        ],
        "tight_strings": []
    },
    "is_malicious": false
}